my_topsis_package/__init__.py
my_topsis_package/__main__.py
my_topsis_package/topsis.py
thapar_102218071_topsis-0.1.dist-info/LICENSE
thapar_102218071_topsis-0.1.dist-info/METADATA
thapar_102218071_topsis-0.1.dist-info/WHEEL
thapar_102218071_topsis-0.1.dist-info/entry_points.txt
thapar_102218071_topsis-0.1.dist-info/top_level.txt
thapar_102218071_topsis-0.1.dist-info/RECORD
